cantorProject/__init__.py
cantorProject/network.py
cantorProject/sci_trainer.py
cantorProject/tfp_trainer.py
cantorProject-0.0.3.dist-info/LICENSE
cantorProject-0.0.3.dist-info/METADATA
cantorProject-0.0.3.dist-info/WHEEL
cantorProject-0.0.3.dist-info/top_level.txt
cantorProject-0.0.3.dist-info/RECORD
