Metadata-Version: 2.1
Name: cantorProject
Version: 0.0.3
Summary: A set of tools to numerically solve differential equations using Neural Networks.
Home-page: https://github.com/VANRao-Stack/cantorProject
Author: V Abhijith Rao
Author-email: varsg007@gmail.com
License: UNKNOWN
Platform: UNKNOWN
Classifier: Programming Language :: Python :: 3
Classifier: License :: OSI Approved :: MIT License
Classifier: Operating System :: OS Independent
Requires-Python: >=3.6
Requires-Dist: tensorflow (>=2.4.0)
Requires-Dist: tensorflow-probability (>=0.12.0)
Requires-Dist: numpy (>=1.19.4)
Requires-Dist: scipy (>=1.4.1)
